CHANGES.txt
README.txt
bootstrap.py
buildout.cfg
setup.py
src/zope/__init__.py
src/zope.app.intid.egg-info/PKG-INFO
src/zope.app.intid.egg-info/SOURCES.txt
src/zope.app.intid.egg-info/dependency_links.txt
src/zope.app.intid.egg-info/namespace_packages.txt
src/zope.app.intid.egg-info/not-zip-safe
src/zope.app.intid.egg-info/requires.txt
src/zope.app.intid.egg-info/top_level.txt
src/zope/app/__init__.py
src/zope/app/intid/__init__.py
src/zope/app/intid/configure.zcml
src/zope/app/intid/ftesting.zcml
src/zope/app/intid/interfaces.py
src/zope/app/intid/subscribers.zcml
src/zope/app/intid/testing.py
src/zope/app/intid/tests.py
src/zope/app/intid/browser/__init__.py
src/zope/app/intid/browser/configure.zcml
src/zope/app/intid/browser/intids.png
src/zope/app/intid/browser/registrations.pt
src/zope/app/intid/browser/tests.py
src/zope/app/intid/browser/tracking.txt